README.md
setup.py
python_xclarityclient.egg-info/PKG-INFO
python_xclarityclient.egg-info/SOURCES.txt
python_xclarityclient.egg-info/dependency_links.txt
python_xclarityclient.egg-info/entry_points.txt
python_xclarityclient.egg-info/not-zip-safe
python_xclarityclient.egg-info/top_level.txt
xclarity_client/__init__.py
xclarity_client/client.py
xclarity_client/constants.py
xclarity_client/exceptions.py
xclarity_client/xclarity_client.py
xclarity_client/v1_2_2/__init__.py
xclarity_client/v1_2_2/boot_order.py
xclarity_client/v1_2_2/client.py