Metadata-Version: 1.1
Name: python-xclarityclient
Version: 0.1.7
Summary: This is a Python library for controlling XClarity by REST API. 
Home-page: UNKNOWN
Author: Finix Lei
Author-email: leilei4@lenovo.com
License: Apache License, Version 2.0
Platform: UNKNOWN
Classifier: Development Status :: 3 - Alpha
Classifier: Environment :: Web Environment
Classifier: Intended Audience :: Developers
Classifier: Operating System :: OS Independent
Classifier: Programming Language :: Python
